eqsql/__init__.py
eqsql/cfg.py
eqsql/db_tools.py
eqsql/proxies.py
eqsql/worker_pool.py
eqsql/workflow.sql
eqsql/task_queues/__init__.py
eqsql/task_queues/core.py
eqsql/task_queues/emews_service.py
eqsql/task_queues/gc_queue.py
eqsql/task_queues/local_queue.py
eqsql/task_queues/remote_funcs.py
eqsql/task_queues/service_queue.py
test/__init__.py
test/common.py
test/test_eq.py
test/test_gc_queue.py
test/test_pools.py
test/test_service_queue.py
test/utils.py
eqsql-0.13.0.dist-info/LICENSE.txt
eqsql-0.13.0.dist-info/METADATA
eqsql-0.13.0.dist-info/WHEEL
eqsql-0.13.0.dist-info/top_level.txt
eqsql-0.13.0.dist-info/RECORD
