Metadata-Version: 2.1
Name: eqsql
Version: 0.13.0
Summary: The eqsql package provies an API for HPC workflows to submit, run, and retrieve tasks (such as simulation model runs) using queues implemented in a database.
Home-page: https://github.com/emews/EQ-SQL
Author: Nick Collier
Author-email: ncollier@anl.gov
Maintainer: Nick Collier
Maintainer-email: ncollier@anl.gov
License: BSD 3-Clause License
Project-URL: Bug Tracker, https://github.com/emews/EQ-SQL/issues
Project-URL: Documentation, https://github.com/emews/EQ-SQL#readme
Project-URL: Git Repository, https://github.com/emews/EQ-SQL
Classifier: Development Status :: 4 - Beta
Classifier: Intended Audience :: Science/Research
Classifier: License :: OSI Approved :: BSD License
Classifier: Operating System :: POSIX :: Linux
Classifier: Operating System :: MacOS
Classifier: Operating System :: Microsoft :: Windows
Classifier: Programming Language :: Python :: 3
Classifier: Topic :: Scientific/Engineering
Classifier: Topic :: System :: Distributed Computing
Requires-Python: >=3.8
License-File: LICENSE.txt
Requires-Dist: dill
Requires-Dist: proxystore
Requires-Dist: psij-python
Requires-Dist: psutil
Requires-Dist: psycopg2-binary
Requires-Dist: globus-compute-sdk
Requires-Dist: pyyaml
